pybigparser/__init__.py
pybigparser/evaluator.py
pyBigParser-2.2.dist-info/LICENSE
pyBigParser-2.2.dist-info/METADATA
pyBigParser-2.2.dist-info/WHEEL
pyBigParser-2.2.dist-info/top_level.txt
pyBigParser-2.2.dist-info/RECORD
