Metadata-Version: 2.1
Name: pyBigParser
Version: 2.2
Summary: Math parser for simple and compound strings math expressions evaluations
Home-page: https://github.com/carrasquel/pybigparser
Author: Nelson Carrasquel
Author-email: carrasquel@outlook.com
License: BSD License
Platform: UNKNOWN
Classifier: Programming Language :: Python :: 3
Classifier: License :: OSI Approved :: MIT License
Classifier: Operating System :: OS Independent
